[
    {
        "imgname": "num_0.png",
        "query": "not used",
        "label": [
            36,
            41,
            97
        ]
    },
    {
        "imgname": "num_1.png",
        "query": "not used",
        "label": [
            30,
            86,
            52
        ]
    },
    {
        "imgname": "num_2.png",
        "query": "not used",
        "label": [
            56,
            99,
            45,
            54,
            52,
            30,
            66,
            42,
            18,
            91
        ]
    },
    {
        "imgname": "num_3.png",
        "query": "not used",
        "label": [
            17,
            86,
            78
        ]
    },
    {
        "imgname": "num_4.png",
        "query": "not used",
        "label": [
            83,
            55,
            52,
            47,
            79,
            24,
            16,
            16
        ]
    },
    {
        "imgname": "num_5.png",
        "query": "not used",
        "label": [
            83,
            63,
            31,
            78,
            33,
            64,
            57
        ]
    },
    {
        "imgname": "num_6.png",
        "query": "not used",
        "label": [
            97,
            32,
            5,
            94,
            47,
            19
        ]
    },
    {
        "imgname": "num_7.png",
        "query": "not used",
        "label": [
            76,
            60,
            83
        ]
    },
    {
        "imgname": "num_8.png",
        "query": "not used",
        "label": [
            31,
            28,
            16,
            82,
            73,
            87,
            58,
            45,
            73
        ]
    },
    {
        "imgname": "num_9.png",
        "query": "not used",
        "label": [
            32,
            87,
            20,
            54,
            100,
            42,
            55,
            29
        ]
    },
    {
        "imgname": "num_10.png",
        "query": "not used",
        "label": [
            57,
            67,
            3,
            2,
            70,
            38,
            95
        ]
    },
    {
        "imgname": "num_11.png",
        "query": "not used",
        "label": [
            49,
            20,
            15,
            81,
            30,
            95,
            88,
            88
        ]
    },
    {
        "imgname": "num_12.png",
        "query": "not used",
        "label": [
            88,
            91,
            91,
            60,
            46,
            28,
            21,
            90,
            11,
            20,
            12
        ]
    },
    {
        "imgname": "num_13.png",
        "query": "not used",
        "label": [
            88,
            95,
            11,
            1,
            50,
            75
        ]
    },
    {
        "imgname": "num_14.png",
        "query": "not used",
        "label": [
            94,
            67,
            32,
            28,
            12,
            67,
            13,
            54
        ]
    },
    {
        "imgname": "num_15.png",
        "query": "not used",
        "label": [
            15,
            96,
            18,
            75,
            6,
            22
        ]
    },
    {
        "imgname": "num_16.png",
        "query": "not used",
        "label": [
            89,
            3,
            70
        ]
    },
    {
        "imgname": "num_17.png",
        "query": "not used",
        "label": [
            47,
            10,
            79,
            45,
            11,
            43,
            100,
            27,
            0,
            8,
            19,
            29
        ]
    },
    {
        "imgname": "num_18.png",
        "query": "not used",
        "label": [
            51,
            60,
            27,
            77,
            99,
            70,
            64,
            12,
            30
        ]
    },
    {
        "imgname": "num_19.png",
        "query": "not used",
        "label": [
            64,
            80,
            73,
            43
        ]
    },
    {
        "imgname": "num_20.png",
        "query": "not used",
        "label": [
            55,
            60,
            5,
            49,
            57,
            48,
            24,
            83,
            5,
            98,
            15,
            47
        ]
    },
    {
        "imgname": "num_21.png",
        "query": "not used",
        "label": [
            99,
            61,
            77
        ]
    },
    {
        "imgname": "num_22.png",
        "query": "not used",
        "label": [
            91,
            58,
            58
        ]
    },
    {
        "imgname": "num_23.png",
        "query": "not used",
        "label": [
            46,
            54,
            16,
            7
        ]
    },
    {
        "imgname": "num_24.png",
        "query": "not used",
        "label": [
            20,
            80,
            97,
            77,
            72,
            42,
            80,
            28,
            41,
            52,
            88,
            55
        ]
    },
    {
        "imgname": "num_25.png",
        "query": "not used",
        "label": [
            78,
            77,
            1,
            84,
            13,
            95,
            75
        ]
    },
    {
        "imgname": "num_26.png",
        "query": "not used",
        "label": [
            48,
            5,
            90,
            71,
            98,
            74
        ]
    },
    {
        "imgname": "num_27.png",
        "query": "not used",
        "label": [
            96,
            25,
            68,
            89,
            19,
            19,
            42
        ]
    },
    {
        "imgname": "num_28.png",
        "query": "not used",
        "label": [
            4,
            56,
            2,
            54,
            93,
            0,
            47
        ]
    },
    {
        "imgname": "num_29.png",
        "query": "not used",
        "label": [
            64,
            76,
            93,
            49,
            90,
            29,
            32,
            47,
            49,
            99,
            63
        ]
    },
    {
        "imgname": "num_30.png",
        "query": "not used",
        "label": [
            36,
            75,
            14,
            6,
            18,
            60,
            81,
            86,
            52,
            37,
            0,
            70
        ]
    },
    {
        "imgname": "num_31.png",
        "query": "not used",
        "label": [
            34,
            48,
            23,
            47,
            71,
            4,
            84,
            52,
            94,
            22,
            15,
            71
        ]
    },
    {
        "imgname": "num_32.png",
        "query": "not used",
        "label": [
            88,
            19,
            11,
            38,
            93
        ]
    },
    {
        "imgname": "num_33.png",
        "query": "not used",
        "label": [
            31,
            65,
            25,
            32,
            54
        ]
    },
    {
        "imgname": "num_34.png",
        "query": "not used",
        "label": [
            65,
            56,
            92,
            71,
            65,
            85
        ]
    },
    {
        "imgname": "num_35.png",
        "query": "not used",
        "label": [
            48,
            0,
            43,
            29,
            96,
            73,
            95,
            39,
            41,
            29
        ]
    },
    {
        "imgname": "num_36.png",
        "query": "not used",
        "label": [
            88,
            52,
            58,
            53,
            66,
            64,
            55,
            8,
            97,
            48
        ]
    },
    {
        "imgname": "num_37.png",
        "query": "not used",
        "label": [
            97,
            3,
            46,
            25,
            12,
            13,
            99,
            4,
            53,
            67,
            33
        ]
    },
    {
        "imgname": "num_38.png",
        "query": "not used",
        "label": [
            38,
            54,
            98,
            9,
            82,
            26,
            54,
            77,
            17,
            36
        ]
    },
    {
        "imgname": "num_39.png",
        "query": "not used",
        "label": [
            32,
            72,
            16,
            39,
            33,
            22,
            8,
            44,
            87,
            94,
            76,
            65
        ]
    },
    {
        "imgname": "num_40.png",
        "query": "not used",
        "label": [
            70,
            82,
            65,
            60,
            31
        ]
    },
    {
        "imgname": "num_41.png",
        "query": "not used",
        "label": [
            88,
            65,
            79,
            31,
            34,
            27,
            66,
            72,
            79,
            97,
            85,
            85
        ]
    },
    {
        "imgname": "num_42.png",
        "query": "not used",
        "label": [
            11,
            51,
            31,
            7,
            80,
            82,
            8,
            25,
            95
        ]
    },
    {
        "imgname": "num_43.png",
        "query": "not used",
        "label": [
            61,
            41,
            70,
            76,
            70,
            34,
            0,
            17,
            82,
            93
        ]
    },
    {
        "imgname": "num_44.png",
        "query": "not used",
        "label": [
            2,
            51,
            24,
            50,
            14,
            76,
            39,
            29,
            67,
            93,
            9
        ]
    },
    {
        "imgname": "num_45.png",
        "query": "not used",
        "label": [
            50,
            48,
            51,
            36,
            48,
            22,
            98,
            2
        ]
    },
    {
        "imgname": "num_46.png",
        "query": "not used",
        "label": [
            80,
            98,
            16,
            41
        ]
    },
    {
        "imgname": "num_47.png",
        "query": "not used",
        "label": [
            36,
            16,
            53
        ]
    },
    {
        "imgname": "num_48.png",
        "query": "not used",
        "label": [
            43,
            30,
            38,
            32,
            82,
            16,
            79,
            57,
            27
        ]
    },
    {
        "imgname": "num_49.png",
        "query": "not used",
        "label": [
            11,
            7,
            91
        ]
    },
    {
        "imgname": "num_50.png",
        "query": "not used",
        "label": [
            90,
            25,
            65,
            86,
            26,
            77
        ]
    },
    {
        "imgname": "num_51.png",
        "query": "not used",
        "label": [
            94,
            86,
            77,
            16,
            74,
            93
        ]
    },
    {
        "imgname": "num_52.png",
        "query": "not used",
        "label": [
            62,
            51,
            30
        ]
    },
    {
        "imgname": "num_53.png",
        "query": "not used",
        "label": [
            68,
            40,
            62,
            63,
            10,
            89
        ]
    },
    {
        "imgname": "num_54.png",
        "query": "not used",
        "label": [
            20,
            2,
            9,
            4,
            47,
            3,
            39,
            18,
            49,
            30,
            55
        ]
    },
    {
        "imgname": "num_55.png",
        "query": "not used",
        "label": [
            79,
            99,
            100,
            47,
            58,
            99,
            25
        ]
    },
    {
        "imgname": "num_56.png",
        "query": "not used",
        "label": [
            18,
            99,
            22,
            25,
            45,
            98,
            78,
            91,
            1,
            65
        ]
    },
    {
        "imgname": "num_57.png",
        "query": "not used",
        "label": [
            7,
            31,
            72,
            58,
            32,
            87
        ]
    },
    {
        "imgname": "num_58.png",
        "query": "not used",
        "label": [
            21,
            17,
            83,
            13,
            52,
            97,
            4,
            36
        ]
    },
    {
        "imgname": "num_59.png",
        "query": "not used",
        "label": [
            44,
            52,
            70,
            61,
            86,
            26
        ]
    },
    {
        "imgname": "num_60.png",
        "query": "not used",
        "label": [
            40,
            28,
            39,
            85,
            33,
            7
        ]
    },
    {
        "imgname": "num_61.png",
        "query": "not used",
        "label": [
            98,
            65,
            31,
            25,
            45
        ]
    },
    {
        "imgname": "num_62.png",
        "query": "not used",
        "label": [
            16,
            46,
            49,
            53,
            93,
            90,
            25,
            83,
            28
        ]
    },
    {
        "imgname": "num_63.png",
        "query": "not used",
        "label": [
            7,
            55,
            76,
            57,
            81,
            77
        ]
    },
    {
        "imgname": "num_64.png",
        "query": "not used",
        "label": [
            28,
            84,
            30,
            90,
            25
        ]
    },
    {
        "imgname": "num_65.png",
        "query": "not used",
        "label": [
            14,
            82,
            10,
            9,
            75,
            52,
            73,
            10,
            66,
            30
        ]
    },
    {
        "imgname": "num_66.png",
        "query": "not used",
        "label": [
            59,
            51,
            94,
            47,
            79,
            6
        ]
    },
    {
        "imgname": "num_67.png",
        "query": "not used",
        "label": [
            60,
            43,
            81,
            62,
            57,
            56
        ]
    },
    {
        "imgname": "num_68.png",
        "query": "not used",
        "label": [
            43,
            63,
            100,
            70,
            7,
            0
        ]
    },
    {
        "imgname": "num_69.png",
        "query": "not used",
        "label": [
            63,
            42,
            49,
            73,
            11,
            67,
            31,
            9,
            56,
            31,
            74,
            57
        ]
    },
    {
        "imgname": "num_70.png",
        "query": "not used",
        "label": [
            45,
            6,
            39
        ]
    },
    {
        "imgname": "num_71.png",
        "query": "not used",
        "label": [
            54,
            85,
            15,
            24,
            99,
            40,
            83,
            54,
            91,
            64,
            44
        ]
    },
    {
        "imgname": "num_72.png",
        "query": "not used",
        "label": [
            12,
            18,
            98,
            9,
            87,
            89,
            97,
            61,
            78,
            0
        ]
    },
    {
        "imgname": "num_73.png",
        "query": "not used",
        "label": [
            68,
            61,
            9,
            4,
            10,
            10
        ]
    },
    {
        "imgname": "num_74.png",
        "query": "not used",
        "label": [
            38,
            60,
            3,
            80,
            18,
            29,
            98
        ]
    },
    {
        "imgname": "num_75.png",
        "query": "not used",
        "label": [
            10,
            86,
            90,
            76,
            58,
            56,
            15,
            9,
            16
        ]
    },
    {
        "imgname": "num_76.png",
        "query": "not used",
        "label": [
            70,
            21,
            47,
            41
        ]
    },
    {
        "imgname": "num_77.png",
        "query": "not used",
        "label": [
            30,
            76,
            26,
            81,
            49,
            72,
            15,
            30,
            57
        ]
    },
    {
        "imgname": "num_78.png",
        "query": "not used",
        "label": [
            33,
            51,
            13,
            34,
            36,
            100,
            2,
            31,
            18
        ]
    },
    {
        "imgname": "num_79.png",
        "query": "not used",
        "label": [
            97,
            77,
            3,
            87,
            81,
            37,
            81,
            66
        ]
    },
    {
        "imgname": "num_80.png",
        "query": "not used",
        "label": [
            53,
            2,
            39,
            48
        ]
    },
    {
        "imgname": "num_81.png",
        "query": "not used",
        "label": [
            14,
            72,
            18,
            28,
            62,
            8,
            40,
            63
        ]
    },
    {
        "imgname": "num_82.png",
        "query": "not used",
        "label": [
            45,
            97,
            79,
            38,
            99
        ]
    },
    {
        "imgname": "num_83.png",
        "query": "not used",
        "label": [
            1,
            17,
            63,
            16
        ]
    },
    {
        "imgname": "num_84.png",
        "query": "not used",
        "label": [
            33,
            36,
            5,
            13,
            40,
            72,
            83,
            22,
            90,
            27
        ]
    },
    {
        "imgname": "num_85.png",
        "query": "not used",
        "label": [
            60,
            28,
            56,
            23,
            74,
            13
        ]
    },
    {
        "imgname": "num_86.png",
        "query": "not used",
        "label": [
            9,
            71,
            62,
            52,
            29,
            50,
            20,
            21
        ]
    },
    {
        "imgname": "num_87.png",
        "query": "not used",
        "label": [
            71,
            3,
            79
        ]
    },
    {
        "imgname": "num_88.png",
        "query": "not used",
        "label": [
            50,
            38,
            7,
            42
        ]
    },
    {
        "imgname": "num_89.png",
        "query": "not used",
        "label": [
            36,
            54,
            50,
            80
        ]
    },
    {
        "imgname": "num_90.png",
        "query": "not used",
        "label": [
            88,
            25,
            58,
            96
        ]
    },
    {
        "imgname": "num_91.png",
        "query": "not used",
        "label": [
            65,
            7,
            35,
            87,
            6,
            35,
            20
        ]
    },
    {
        "imgname": "num_92.png",
        "query": "not used",
        "label": [
            44,
            94,
            61,
            72,
            82,
            2,
            8,
            15,
            33,
            1
        ]
    },
    {
        "imgname": "num_93.png",
        "query": "not used",
        "label": [
            80,
            14,
            23,
            31,
            30,
            24,
            84,
            16
        ]
    },
    {
        "imgname": "num_94.png",
        "query": "not used",
        "label": [
            88,
            78,
            96,
            84,
            45,
            45,
            32,
            27,
            79,
            55,
            32,
            31
        ]
    },
    {
        "imgname": "num_95.png",
        "query": "not used",
        "label": [
            80,
            47,
            52,
            81,
            15,
            99
        ]
    },
    {
        "imgname": "num_96.png",
        "query": "not used",
        "label": [
            81,
            34,
            88,
            54,
            27,
            66,
            62,
            43,
            27,
            43,
            13
        ]
    },
    {
        "imgname": "num_97.png",
        "query": "not used",
        "label": [
            34,
            95,
            56,
            40,
            10,
            29,
            4,
            42,
            22,
            52,
            22,
            95
        ]
    },
    {
        "imgname": "num_98.png",
        "query": "not used",
        "label": [
            72,
            69,
            6,
            78,
            89,
            66,
            44,
            34,
            54,
            100
        ]
    },
    {
        "imgname": "num_99.png",
        "query": "not used",
        "label": [
            53,
            42,
            42,
            50,
            96,
            20,
            52,
            35,
            32,
            72,
            48
        ]
    }
]